sppyte/__about__.py
sppyte/__init__.py
sppyte/errors.py
sppyte/models.py
sppyte/utils.py
sppyte-0.1.7.dist-info/METADATA
sppyte-0.1.7.dist-info/WHEEL
sppyte-0.1.7.dist-info/licenses/LICENSE
sppyte-0.1.7.dist-info/RECORD
