Metadata-Version: 2.4
Name: sppyte
Version: 0.1.7
Summary: Common tasks with SharePoint REST service
Project-URL: Documentation, https://github.com/B-Jones-RFD/sppyte#readme
Project-URL: Issues, https://github.com/B-Jones-RFD/sppyte/issues
Project-URL: Source, https://github.com/B-Jones-RFD/sppyte
Author: B-Jones-RFD
License-Expression: MIT
License-File: LICENSE
Classifier: Development Status :: 3 - Alpha
Classifier: Programming Language :: Python
Classifier: Programming Language :: Python :: 3.10
Classifier: Programming Language :: Python :: 3.11
Classifier: Programming Language :: Python :: 3.12
Classifier: Programming Language :: Python :: Implementation :: CPython
Classifier: Programming Language :: Python :: Implementation :: PyPy
Requires-Python: >=3.10
Requires-Dist: requests-ntlm
